ultimate_notion/__init__.py
ultimate_notion/_version.py
ultimate_notion/blocks.py
ultimate_notion/cli.py
ultimate_notion/comment.py
ultimate_notion/config.py
ultimate_notion/core.py
ultimate_notion/database.py
ultimate_notion/emoji.py
ultimate_notion/errors.py
ultimate_notion/file.py
ultimate_notion/markdown.py
ultimate_notion/option.py
ultimate_notion/page.py
ultimate_notion/props.py
ultimate_notion/py.typed
ultimate_notion/query.py
ultimate_notion/rich_text.py
ultimate_notion/schema.py
ultimate_notion/session.py
ultimate_notion/user.py
ultimate_notion/utils.py
ultimate_notion/view.py
ultimate_notion/adapters/__init__.py
ultimate_notion/adapters/sync.py
ultimate_notion/adapters/google/__init__.py
ultimate_notion/adapters/google/tasks/__init__.py
ultimate_notion/adapters/google/tasks/client.py
ultimate_notion/adapters/google/tasks/sync.py
ultimate_notion/obj_api/__init__.py
ultimate_notion/obj_api/blocks.py
ultimate_notion/obj_api/core.py
ultimate_notion/obj_api/endpoints.py
ultimate_notion/obj_api/enums.py
ultimate_notion/obj_api/iterator.py
ultimate_notion/obj_api/objects.py
ultimate_notion/obj_api/props.py
ultimate_notion/obj_api/query.py
ultimate_notion/obj_api/schema.py
ultimate_notion/templates/__init__.py
ultimate_notion/templates/page.html
ultimate_notion-0.9.5.dist-info/METADATA
ultimate_notion-0.9.5.dist-info/WHEEL
ultimate_notion-0.9.5.dist-info/entry_points.txt
ultimate_notion-0.9.5.dist-info/licenses/AUTHORS.md
ultimate_notion-0.9.5.dist-info/licenses/LICENSE.txt
ultimate_notion-0.9.5.dist-info/RECORD
