Metadata-Version: 2.4
Name: ultimate-notion
Version: 0.9.5
Summary: The ultimate Python client for Notion!
Project-URL: Homepage, https://ultimate-notion.com
Project-URL: Documentation, https://ultimate-notion.com/latest/usage/getting_started/
Project-URL: Download, https://pypi.org/project/ultimate-notion/#files
Project-URL: Source, https://github.com/ultimate-notion/ultimate-notion
Project-URL: Changelog, https://ultimate-notion.com/latest/changelog/
Project-URL: Tracker, https://github.com/ultimate-notion/ultimate-notion/issues
Project-URL: Sponsor, https://github.com/sponsors/FlorianWilhelm
Author-email: Florian Wilhelm <Florian.Wilhelm@gmail.com>
License-Expression: MIT
License-File: AUTHORS.md
License-File: LICENSE.txt
Keywords: notion,notion client
Classifier: Development Status :: 4 - Beta
Classifier: License :: OSI Approved :: MIT License
Classifier: Programming Language :: Python
Classifier: Programming Language :: Python :: 3.10
Classifier: Programming Language :: Python :: 3.11
Classifier: Programming Language :: Python :: 3.12
Classifier: Programming Language :: Python :: 3.13
Classifier: Programming Language :: Python :: Implementation :: CPython
Classifier: Topic :: Office/Business
Classifier: Topic :: Software Development :: Libraries
Classifier: Topic :: Utilities
Classifier: Typing :: Typed
Requires-Python: >=3.10
Requires-Dist: emoji>=2.8
Requires-Dist: filetype>=1.2
Requires-Dist: httpx>=0.27
Requires-Dist: mistune>=3.0
Requires-Dist: notion-client~=2.5.0
Requires-Dist: numpy>=1.24
Requires-Dist: packaging
Requires-Dist: pendulum>=3.0
Requires-Dist: pydantic>=2.0
Requires-Dist: tabulate>=0.9
Requires-Dist: tomli-w>=1.2
Requires-Dist: tomli>=2.2
Requires-Dist: typer>=0.16
Requires-Dist: typing-extensions
Requires-Dist: url-normalize>=2.2
Provides-Extra: all
Requires-Dist: google-api-python-client; extra == 'all'
Requires-Dist: google-auth-httplib2; extra == 'all'
Requires-Dist: google-auth-oauthlib; extra == 'all'
Requires-Dist: pandas>=2.0; extra == 'all'
Requires-Dist: polars>=1.17; extra == 'all'
Provides-Extra: google
Requires-Dist: google-api-python-client; extra == 'google'
Requires-Dist: google-auth-httplib2; extra == 'google'
Requires-Dist: google-auth-oauthlib; extra == 'google'
Provides-Extra: pandas
Requires-Dist: pandas>=2.0; extra == 'pandas'
Provides-Extra: polars
Requires-Dist: polars>=1.17; extra == 'polars'
